README.rst
setup.py
jinja2_highlight/__init__.py
jinja2_highlight/highlight.py
jinja2_highlight.egg-info/PKG-INFO
jinja2_highlight.egg-info/SOURCES.txt
jinja2_highlight.egg-info/dependency_links.txt
jinja2_highlight.egg-info/requires.txt
jinja2_highlight.egg-info/top_level.txt