Metadata-Version: 1.1
Name: jinja2-highlight
Version: 0.5.0
Summary: Jinja2 extension to highlight source code using Pygments
Home-page: https://github.com/tlatsas/jinja2-highlight
Author: Tasos Latsas
Author-email: tlatsas2000@gmail.com
License: GNU GPLv3
Keywords: syntax highlighting
Platform: UNKNOWN
Classifier: Development Status :: 4 - Beta
Classifier: Environment :: Web Environment
Classifier: Intended Audience :: Developers
Classifier: License :: OSI Approved :: GNU General Public License v3 (GPLv3)
Classifier: Programming Language :: Python
Classifier: Programming Language :: Python :: 2.7
Classifier: Programming Language :: Python :: 3
Classifier: Topic :: Internet :: WWW/HTTP :: Dynamic Content
Classifier: Topic :: Software Development :: Libraries :: Python Modules
Classifier: Topic :: Text Processing :: Markup :: HTML
